django_turnstile_htmx-0.1.0.dist-info/licenses/LICENSE
turnstile_htmx/__init__.py
turnstile_htmx/apps.py
turnstile_htmx/decorators.py
turnstile_htmx/templatetags/__init__.py
turnstile_htmx/templatetags/turnstile_tags.py
turnstile_htmx/tests/__init__.py
turnstile_htmx/tests/integration_test.py
turnstile_htmx/tests/templatetags_test.py
turnstile_htmx/tests/test_project/settings.py
django_turnstile_htmx-0.1.0.dist-info/METADATA
django_turnstile_htmx-0.1.0.dist-info/WHEEL
django_turnstile_htmx-0.1.0.dist-info/top_level.txt
django_turnstile_htmx-0.1.0.dist-info/RECORD
