Metadata-Version: 2.4
Name: django-turnstile-htmx
Version: 0.1.0
Summary: A Django app for integrating Cloudflare Turnstile CAPTCHA protection with support for HTMX.
Author-email: Your Name <you@example.com>
License: MIT
Project-URL: Homepage, https://github.com/your-username/django-turnstile-htmx
Project-URL: Issues, https://github.com/your-username/django-turnstile-htmx/issues
Classifier: Environment :: Web Environment
Classifier: Framework :: Django
Classifier: Framework :: Django :: 4.2
Classifier: Framework :: Django :: 5.0
Classifier: Intended Audience :: Developers
Classifier: License :: OSI Approved :: MIT License
Classifier: Operating System :: OS Independent
Classifier: Programming Language :: Python
Classifier: Programming Language :: Python :: 3
Classifier: Programming Language :: Python :: 3.8
Classifier: Programming Language :: Python :: 3.9
Classifier: Programming Language :: Python :: 3.10
Classifier: Programming Language :: Python :: 3.11
Classifier: Programming Language :: Python :: 3.12
Requires-Python: >=3.8
License-File: LICENSE
Requires-Dist: django>=4.2
Requires-Dist: requests
Provides-Extra: test
Requires-Dist: pytest; extra == "test"
Requires-Dist: pytest-django; extra == "test"
Dynamic: license-file
